pdf_layout_scanner/__init__.py
pdf_layout_scanner/__main__.py
pdf_layout_scanner/layout_scanner.py
PDF_Layout_Scanner-1.3.3.dist-info/LICENSE
PDF_Layout_Scanner-1.3.3.dist-info/METADATA
PDF_Layout_Scanner-1.3.3.dist-info/WHEEL
PDF_Layout_Scanner-1.3.3.dist-info/top_level.txt
PDF_Layout_Scanner-1.3.3.dist-info/RECORD
