Metadata-Version: 2.1
Name: PDF-Layout-Scanner
Version: 1.3.3
Summary: UNKNOWN
Home-page: https://github.com/yoshihikoueno/pdfminer-layout-scanner
Author: Yoshihiko Ueno
Author-email: windows7home@hotmail.co.jp
License: MIT
Platform: UNKNOWN
Requires-Dist: pandas
Requires-Dist: tqdm
Requires-Dist: pdfminer.six
